setup.cfg
setup.py
ansible_mikrotik_utils.egg-info/PKG-INFO
ansible_mikrotik_utils.egg-info/SOURCES.txt
ansible_mikrotik_utils.egg-info/dependency_links.txt
ansible_mikrotik_utils.egg-info/top_level.txt
src/ansible_mikrotik_utils/__init__.py
src/ansible_mikrotik_utils/base.py
src/ansible_mikrotik_utils/common.py
src/ansible_mikrotik_utils/exceptions.py
src/ansible_mikrotik_utils/mixins.py
src/ansible_mikrotik_utils/objects.py
src/ansible_mikrotik_utils/script.py
src/ansible_mikrotik_utils/commands/__init__.py
src/ansible_mikrotik_utils/commands/backup.py
src/ansible_mikrotik_utils/commands/base.py
src/ansible_mikrotik_utils/commands/config.py
src/ansible_mikrotik_utils/commands/mixins.py
src/ansible_mikrotik_utils/commands/scheduler.py
src/ansible_mikrotik_utils/commands/script.py
src/ansible_mikrotik_utils/device/__init__.py
src/ansible_mikrotik_utils/sections/__init__.py
src/ansible_mikrotik_utils/sections/base.py
src/ansible_mikrotik_utils/sections/config.py
src/ansible_mikrotik_utils/sections/mixins.py
src/ansible_mikrotik_utils/sections/paths.py
src/ansible_mikrotik_utils/sections/scheduler.py
src/ansible_mikrotik_utils/sections/script.py