Metadata-Version: 1.1
Name: ansible-mikrotik-utils
Version: 0.0.3
Summary: This module provides code that can parse exported configurations from
